pepega/core/__init__.py
pepega/core/core.py
pepega/utils/__init__.py
pepega/utils/utils.py
pepega-0.1.0.dist-info/LICENSE
pepega-0.1.0.dist-info/METADATA
pepega-0.1.0.dist-info/WHEEL
pepega-0.1.0.dist-info/top_level.txt
pepega-0.1.0.dist-info/RECORD
