Metadata-Version: 2.1
Name: pepega
Version: 0.1.0
Summary: A modular MLP package
Author-email: Vsevolod Prudius <vsevolod.prudius@mlprograms.com>
License: Copyright 2024 Vsevolod Prudius
Project-URL: homepage, https://gitlab.mlprograms.com/mlp/pepega
Project-URL: repository, https://gitlab.mlprograms.com/mlp/pepega
Project-URL: documentation, https://gitlab.mlprograms.com/mlp/pepega/docs
Requires-Python: >=3.9
License-File: LICENSE
Requires-Dist: mlp-api-tools
Requires-Dist: requests
Provides-Extra: core
Requires-Dist: pandas >=2.0.0 ; extra == 'core'
Provides-Extra: full
Requires-Dist: pepega[core] ; extra == 'full'
Requires-Dist: pepega[utils] ; extra == 'full'
Provides-Extra: utils
Requires-Dist: numpy >=1.24 ; extra == 'utils'
